AUTHORS
INSTALL
LICENSE
MANIFEST.in
README.rst
setup.cfg
setup.py
Expluit0.egg-info/PKG-INFO
Expluit0.egg-info/SOURCES.txt
Expluit0.egg-info/dependency_links.txt
Expluit0.egg-info/top_level.txt
Expluit0.egg-info/zip-safe
expluit0/Expluit0.py
expluit0/__init__.py
expluit0/copyright.py
expluit0/encoder/__init__.py
expluit0/encoder/pex.py