Metadata-Version: 1.1
Name: Expluit0
Version: 0.4.2
Summary: The Exploit Framework for Your CTF
Home-page: https://github.com/posquit0/Expluit0
Author: Byungjin Park
Author-email: posquit0.bj@gmail.com
License: MIT
Download-URL: https://github.com/posquit0/Expluit0/zipball/0.4.2
Keywords: exploit,ctf,framework,posquit0,system,shellcode,expluit0,expluito,shell
Platform: Linux
Platform: Unix
Platform: Mac OS-X
